hwp_extract/__init__.py
hwp_extract/_version.py
hwp_extract/cli.py
hwp_extract/encrypt.py
hwp_extract/hwp.py
hwp_extract/py.typed
hwp_extract-0.1.0.dist-info/METADATA
hwp_extract-0.1.0.dist-info/WHEEL
hwp_extract-0.1.0.dist-info/entry_points.txt
hwp_extract-0.1.0.dist-info/licenses/LICENSE.md
hwp_extract-0.1.0.dist-info/RECORD
