Metadata-Version: 2.3
Name: hwp-extract
Version: 0.1.0
Summary: Simple object extractor for HWP files.
Project-URL: Documentation, https://github.com/volexity/hwp-extract/blob/master/README.md
Project-URL: Issues, https://github.com/volexity/hwp-extract/issues
Project-URL: Source, https://github.com/volexity/hwp-extract
Author-email: Threat Intel <threatintel@volexity.com>
License: Modified BSD License
Keywords: extractor,hwp
Classifier: Development Status :: 4 - Beta
Classifier: License :: OSI Approved :: BSD License
Classifier: Programming Language :: Python
Classifier: Programming Language :: Python :: 3.9
Classifier: Programming Language :: Python :: 3.10
Classifier: Programming Language :: Python :: 3.11
Classifier: Programming Language :: Python :: 3.12
Classifier: Programming Language :: Python :: Implementation :: CPython
Classifier: Programming Language :: Python :: Implementation :: PyPy
Requires-Python: >=3.9
Requires-Dist: olefile~=0.47
Requires-Dist: pycryptodome~=3.0
